fastapi_restfull/__init__.py
fastapi_restfull/aio/__init__.py
fastapi_restfull/aio/controller/__init__.py
fastapi_restfull/aio/controller/base.py
fastapi_restfull/aio/permissions/__init__.py
fastapi_restfull/aio/permissions/base.py
fastapi_restfull/aio/repository/__init__.py
fastapi_restfull/aio/repository/base.py
fastapi_restfull/aio/service/__init__.py
fastapi_restfull/aio/service/base.py
fastapi_restfull/exceptions/__init__.py
fastapi_restfull/exceptions/api_exceptions.py
fastapi_restfull/exceptions/handler.py
fastapi_restfull/schema/__init__.py
fastapi_restfull/schema/base.py
fastapi_restfull/schema/jwt.py
fastapi_restfull/schema/schema.py
fastapi_restfull/servicios/__init__.py
fastapi_restfull/servicios/thrid/__init__.py
fastapi_restfull/servicios/thrid/jwt.py
fastapi_restfull/servicios/thrid/supabase.py
fastapi_restfull-0.1.2.dist-info/METADATA
fastapi_restfull-0.1.2.dist-info/WHEEL
fastapi_restfull-0.1.2.dist-info/top_level.txt
fastapi_restfull-0.1.2.dist-info/RECORD
