Metadata-Version: 2.4
Name: fastapi-restfull
Version: 0.1.2
Summary: Utilities and base classes for FastAPI async projects using Beanie ODM
Author-email: Jerson Moreno <jerson.ml820@hotmail.com>
License: MIT
Project-URL: Homepage, https://github.com/mundobien2025/fastapi-restfull.git
Classifier: Programming Language :: Python :: 3
Classifier: License :: OSI Approved :: MIT License
Classifier: Framework :: FastAPI
Classifier: Operating System :: OS Independent
Requires-Python: >=3.11
Requires-Dist: fastapi>=0.115.0
Requires-Dist: beanie>=2.0.0
Requires-Dist: pydantic>=2.10.6
Requires-Dist: pyjwt>=2.10.1
Requires-Dist: supabase>=2.13.0
Requires-Dist: aiofiles>=24.1.0
